btc_embedded/__init__.py
btc_embedded/api.py
btc_embedded/config.py
btc_embedded/helpers.py
btc_embedded/migration.py
btc_embedded/reporting.py
btc_embedded/util.py
btc_embedded/resources/btc_config_linux.yml
btc_embedded/resources/btc_config_windows.yml
btc_embedded/resources/btc_summary_report.template
btc_embedded/resources/projectreport_templates/b2b-only-ec.xml
btc_embedded/resources/projectreport_templates/b2b-only-tl.xml
btc_embedded/resources/projectreport_templates/rbt-b2b-ec.xml
btc_embedded/resources/projectreport_templates/rbt-b2b-tl.xml
btc_embedded/resources/projectreport_templates/rbt-ec.xml
btc_embedded/resources/projectreport_templates/rbt-sil-only.xml
btc_embedded/resources/projectreport_templates/rbt-tl.xml
btc_embedded/resources/projectreport_templates/regression-test-ec.xml
btc_embedded/resources/projectreport_templates/regression-test-sil-only.xml
btc_embedded/resources/projectreport_templates/regression-test-tl.xml
btc_embedded-25.3.2.dist-info/licenses/LICENSE.txt
btc_embedded-25.3.2.dist-info/METADATA
btc_embedded-25.3.2.dist-info/WHEEL
btc_embedded-25.3.2.dist-info/top_level.txt
btc_embedded-25.3.2.dist-info/RECORD
