Metadata-Version: 2.4
Name: btc_embedded
Version: 25.3.2
Summary: API wrapper for BTC EmbeddedPlatform REST API
Author-email: Thabo Krick <thabo.krick@btc-embedded.com>, Nathan Drasovean <nathan.drasovean@btc-embedded.com>, Ferdinand Becker <ferdinand.becker@btc-embedded.com>
License-Expression: MIT
Project-URL: Homepage, https://github.com/btc-embedded/btc_embedded
Classifier: Development Status :: 5 - Production/Stable
Classifier: Intended Audience :: Developers
Classifier: Topic :: Software Development :: Testing
Classifier: Programming Language :: Python :: 3.7
Classifier: Programming Language :: Python :: 3.8
Classifier: Programming Language :: Python :: 3.9
Classifier: Programming Language :: Python :: 3.10
Classifier: Programming Language :: Python :: 3.11
Classifier: Programming Language :: Python :: 3.12
Classifier: Programming Language :: Python :: 3.13
License-File: LICENSE.txt
Requires-Dist: requests
Requires-Dist: pyyaml
Dynamic: license-file
